vids_db/__init__.py
vids_db/database.py
vids_db/date.py
vids_db/db_full_text_search.py
vids_db/db_sqlite_video.py
vids_db/models.py
vids_db/version.py
vids_db-1.2.5.dist-info/METADATA
vids_db-1.2.5.dist-info/WHEEL
vids_db-1.2.5.dist-info/top_level.txt
vids_db-1.2.5.dist-info/RECORD
