Metadata-Version: 2.1
Name: vids-db
Version: 1.2.5
Summary: Server running vids_db
Home-page: https://github.com/zackees/vids-db
Author: Zach Vorhies
Author-email: dont@email.me
License: MIT
Classifier: License :: OSI Approved :: MIT License
Classifier: Programming Language :: Python :: 3.6
Classifier: Programming Language :: Python :: 3.9
Classifier: Operating System :: Microsoft :: Windows
Classifier: Operating System :: POSIX
Classifier: Operating System :: MacOS :: MacOS X
Classifier: Environment :: Console
Requires-Python: >=3.6.0
Requires-Dist: types-python-dateutil
Requires-Dist: python-dateutil
Requires-Dist: pydantic
Requires-Dist: Whoosh
Requires-Dist: pytz
Requires-Dist: types-pytz
